<?xml version="1.0" encoding="UTF-8"?>
<MF0 version="1.1" packageUris="http://schema.mathworks.com/mf0/systemcomposer_property/2.13 http://schema.mathworks.com/mf0/systemcomposer_services_proxy/1.2">
  <systemcomposer.profile.Profile type="systemcomposer.profile.Profile" uuid="80e57f05-5bdf-4f69-8fe2-2c541a6af14a">
    <valueTypes type="systemcomposer.property.BooleanType" uuid="d44ad2c5-175e-42d5-9436-0ac78ac75ca0">
      <p_Name>boolean</p_Name>
    </valueTypes>
    <valueTypes type="systemcomposer.property.FloatType" uuid="e571a4b9-a9ab-4997-9417-162ccd5aa5e2">
      <max>1.7976931348623157e+308</max>
      <min>-1.7976931348623157e+308</min>
      <p_Name>double</p_Name>
    </valueTypes>
    <valueTypes type="systemcomposer.property.IntegerType" uuid="10296b31-a9ba-4f7e-9c53-dc511af30908">
      <max>32767</max>
      <min>-32768</min>
      <p_Name>int16</p_Name>
    </valueTypes>
    <valueTypes type="systemcomposer.property.IntegerType" uuid="87d262a1-caa8-4518-875d-09b49bfcfe73">
      <max>2147483647</max>
      <min>-2147483648</min>
      <p_Name>int32</p_Name>
    </valueTypes>
    <valueTypes type="systemcomposer.property.IntegerType" uuid="dfc3dbac-d42b-4692-90f5-b5d026561a4a">
      <max>9223372036854775807</max>
      <min>-9223372036854775808</min>
      <p_Name>int64</p_Name>
    </valueTypes>
    <valueTypes type="systemcomposer.property.IntegerType" uuid="a31345bf-5972-497c-b2bd-dcb7a479bc89">
      <max>127</max>
      <min>-128</min>
      <p_Name>int8</p_Name>
    </valueTypes>
    <valueTypes type="systemcomposer.property.FloatType" uuid="721e4b40-b0c2-4645-8403-bebad24a150e">
      <max>3.4028234663852886e+38</max>
      <min>-3.4028234663852886e+38</min>
      <p_Name>single</p_Name>
    </valueTypes>
    <valueTypes type="systemcomposer.property.StringType" uuid="1b3148b4-26eb-4aeb-aaac-0dcd86184c66">
      <p_Name>string</p_Name>
    </valueTypes>
    <valueTypes type="systemcomposer.property.StringArrayType" uuid="25627f15-ee4c-4498-a17c-137106705963">
      <p_Name>stringArray</p_Name>
    </valueTypes>
    <valueTypes type="systemcomposer.property.IntegerType" uuid="b34462fe-a439-45fa-9d9c-a1593798cdac">
      <max>65535</max>
      <min>0</min>
      <p_Name>uint16</p_Name>
    </valueTypes>
    <valueTypes type="systemcomposer.property.IntegerType" uuid="59086511-614f-4aaf-9fbf-69069180f8d7">
      <max>4294967295</max>
      <min>0</min>
      <p_Name>uint32</p_Name>
    </valueTypes>
    <valueTypes type="systemcomposer.property.IntegerType" uuid="6407cf8b-c23d-4351-a437-69573a345e0f">
      <max>9223372036854775807</max>
      <min>0</min>
      <p_Name>uint64</p_Name>
    </valueTypes>
    <valueTypes type="systemcomposer.property.IntegerType" uuid="28e49e9b-8af8-4cbf-b05b-f2caa3734841">
      <max>255</max>
      <min>0</min>
      <p_Name>uint8</p_Name>
    </valueTypes>
    <p_Name>PowerComponent</p_Name>
    <elemProxy type="systemcomposer.services.proxy.ProxyTarget" uuid="d02468eb-a89c-45eb-bd2a-4b3ad22a3ec8"/>
  </systemcomposer.profile.Profile>
  <systemcomposer.services.proxy.ModelIdentifier type="systemcomposer.services.proxy.ModelIdentifier" uuid="1eb980d4-0aa2-45eb-b1ea-0d0c47c6e1ec">
    <URI>PowerComponent</URI>
    <modelType>PROFILE_MODEL</modelType>
  </systemcomposer.services.proxy.ModelIdentifier>
  <systemcomposer.property.UnitQueryClientWrapper type="systemcomposer.property.UnitQueryClientWrapper" uuid="e3c4e4cd-33e7-49df-bbe1-fea9f76c6a18"/>
</MF0>